setup.py
netcall/__init__.py
netcall/base.py
netcall/base_client.py
netcall/base_service.py
netcall/datastruct.py
netcall/errors.py
netcall/serializer.py
netcall/utils.py
netcall.egg-info/PKG-INFO
netcall.egg-info/SOURCES.txt
netcall.egg-info/dependency_links.txt
netcall.egg-info/requires.txt
netcall.egg-info/top_level.txt
netcall/concurrency/__init__.py
netcall/concurrency/base.py
netcall/concurrency/eventlet.py
netcall/concurrency/futures.py
netcall/concurrency/gevent.py
netcall/concurrency/greenhouse.py
netcall/concurrency/pebble.py
netcall/green/__init__.py
netcall/green/balancer.py
netcall/green/client.py
netcall/green/service.py
netcall/sync/__init__.py
netcall/threading/__init__.py
netcall/threading/balancer.py
netcall/threading/client.py
netcall/threading/service.py
netcall/tornado/__init__.py
netcall/tornado/client.py
netcall/tornado/service.py
tests/__init__.py
tests/base.py
tests/client_mixins.py
tests/rpc_mixins.py
tests/test_eventlet.py
tests/test_gevent.py
tests/test_green_future.py
tests/test_greenhouse.py
tests/test_sync.py
tests/test_threading.py