Metadata-Version: 1.0
Name: netcall
Version: 0.4.1
Summary: A simple Python RPC system (ZeroMQ + Threading/Tornado/Gevent/Eventlet/Greenhouse)
Home-page: http://github.com/aglyzov/netcall
Author: Alexander Glyzov
Author-email: bonoba@gmail.com
License: Modified BSD
Keywords: ZeroMQ ZMQ PyZMQ Thread Threading Tornado Green Greenlet Gevent Eventlet Greenhouse RPC async
Platform: UNKNOWN
